ssh_mcp/__init__.py
ssh_mcp/mcp.py
ssh_mcp/ssh_client.py
ssh_mcp/model/__init__.py
ssh_mcp/model/proxy.py
ssh_mcp_py-0.1.2.dist-info/licenses/LICENSE
ssh_mcp_py-0.1.2.dist-info/METADATA
ssh_mcp_py-0.1.2.dist-info/WHEEL
ssh_mcp_py-0.1.2.dist-info/entry_points.txt
ssh_mcp_py-0.1.2.dist-info/top_level.txt
ssh_mcp_py-0.1.2.dist-info/RECORD
