Metadata-Version: 2.4
Name: ssh-mcp-py
Version: 0.1.2
Summary: A Model Context Protocol for managing and interacting with multiple virtual machines over SSH
Author-email: Sean Dang <sondt.2709@gmail.com>
Maintainer-email: Sean Dang <sondt.2709@gmail.com>
License: MIT
Project-URL: Homepage, https://github.com/sondt2709/ssh-mcp-py
Project-URL: Repository, https://github.com/sondt2709/ssh-mcp-py
Keywords: vm,mcp,llm,automation
Requires-Python: >=3.10
License-File: LICENSE
Requires-Dist: mcp[cli]>=1.13.1
Requires-Dist: paramiko>=4.0.0
Requires-Dist: pydantic>=2.0.0
Requires-Dist: pysocks>=1.7.1
Requires-Dist: python-dotenv>=1.1.1
Dynamic: license-file
